jdfile/__init__.py
jdfile/config.py
jdfile/constants.py
jdfile/defaults.toml
jdfile/jdfile.py
jdfile/cli/__init__.py
jdfile/cli/helpers.py
jdfile/models/__init__.py
jdfile/models/dates.py
jdfile/models/file.py
jdfile/models/project.py
jdfile/utils/__init__.py
jdfile/utils/common.py
jdfile/utils/logging.py
jdfile/utils/nltk.py
jdfile/utils/questions.py
jdfile/utils/strings.py
jdfile/views/__init__.py
jdfile/views/tables.py
jdfile-2.0.1.dist-info/METADATA
jdfile-2.0.1.dist-info/WHEEL
jdfile-2.0.1.dist-info/entry_points.txt
jdfile-2.0.1.dist-info/licenses/LICENSE
jdfile-2.0.1.dist-info/RECORD
