Metadata-Version: 2.4
Name: jdfile
Version: 2.0.1
Summary: File Manager for the Johnny Decimal System
Project-URL: Homepage, https://github.com/natelandau/jdfile
Project-URL: Repository, https://github.com/natelandau/jdfile
Author-email: Nate Landau <github@natenate.org>
License:                     GNU AFFERO GENERAL PUBLIC LICENSE
License-File: LICENSE
Requires-Python: >=3.11
Requires-Dist: dynaconf>=3.2.6
Requires-Dist: inflect>=7.5.0
Requires-Dist: loguru>=0.7.3
Requires-Dist: nltk>=3.9.1
Requires-Dist: questionary>=2.0.1
Requires-Dist: rich>=13.9.4
Requires-Dist: typer>=0.15.1
